fjunkie/CssFile.py
fjunkie/File.py
fjunkie/HtmlFile.py
fjunkie/PyFile.py
fjunkie/Reader.py
fjunkie/Writer.py
fjunkie/__init__.py
fjunkie-0.0.4.dist-info/METADATA
fjunkie-0.0.4.dist-info/WHEEL
fjunkie-0.0.4.dist-info/top_level.txt
fjunkie-0.0.4.dist-info/RECORD
