Metadata-Version: 2.1
Name: fjunkie
Version: 0.0.4
Summary: Take the Reptiviness out of File Reading / Writing
Home-page: UNKNOWN
Author: GalaxyIndieDev
Author-email: <zachnichelson304@gmail.com>
License: UNKNOWN
Keywords: api,file,read,write,utils
Platform: UNKNOWN
Classifier: Development Status :: 1 - Planning
Classifier: Intended Audience :: Developers
Classifier: Programming Language :: Python :: 3
Classifier: Operating System :: Microsoft :: Windows
